{
  "version": "1.0.0",
  "repository": "TechArc-io/studylab-practice",
  "pathwayRelease": "release-foundation-2026",
  "modules": [
    "orientation",
    "semantic-html",
    "css-layout",
    "javascript-foundations",
    "git-github",
    "package-tooling",
    "typescript",
    "react",
    "react-data",
    "react-forms",
    "nextjs",
    "server-data-security",
    "quality-ci",
    "responsible-ai",
    "capstone"
  ],
  "assignments": [
    { "id": "ms-git-collab", "moduleId": "git-github", "path": "assignments/01-git-collaboration.md" },
    { "id": "ms-ts-types", "moduleId": "typescript", "path": "assignments/02-typescript-data-boundary.md" },
    { "id": "ms-react-ui", "moduleId": "react", "path": "assignments/03-react-accessible-list.md" },
    { "id": "ms-next-route", "moduleId": "nextjs", "path": "assignments/04-next-route-action.md" },
    { "id": "ms-realworld-ci", "moduleId": "quality-ci", "path": "assignments/05-quality-ci.md" },
    { "id": "ms-ai-workflow", "moduleId": "responsible-ai", "path": "assignments/06-responsible-ai.md" },
    { "id": "capstone-frontend", "moduleId": "capstone", "path": "assignments/07-capstone.md" }
  ]
}
